prism/__init__.py
prism/config/__init__.py
prism/config/display.py
prism/config/exceptions.py
prism/config/loader.py
prism/config/models.py
prism/config/providers.py
prism/config/py.typed
prism_config-2.1.2.dist-info/METADATA
prism_config-2.1.2.dist-info/WHEEL
prism_config-2.1.2.dist-info/licenses/LICENSE
prism_config-2.1.2.dist-info/RECORD
