Metadata-Version: 2.4
Name: prism-config
Version: 2.1.2
Summary: 🔮 Prism Config - Type-safe configuration with tiered loading, environment overrides, and secret resolution
Project-URL: Homepage, https://github.com/lukeudell/prism-config
Project-URL: Documentation, https://github.com/lukeudell/prism-config#readme
Project-URL: Repository, https://github.com/lukeudell/prism-config
Project-URL: Issues, https://github.com/lukeudell/prism-config/issues
Project-URL: Changelog, https://github.com/lukeudell/prism-config/blob/main/CHANGELOG.md
Author-email: Luke Udell <luke.t.udell@gmail.com>
License: MIT
License-File: LICENSE
Keywords: 12-factor,config,configuration,docker,environment,kubernetes,pydantic,secrets,settings,yaml
Classifier: Development Status :: 5 - Production/Stable
Classifier: Intended Audience :: Developers
Classifier: License :: OSI Approved :: MIT License
Classifier: Operating System :: OS Independent
Classifier: Programming Language :: Python :: 3
Classifier: Programming Language :: Python :: 3.10
Classifier: Programming Language :: Python :: 3.11
Classifier: Programming Language :: Python :: 3.12
Classifier: Topic :: Software Development :: Libraries :: Python Modules
Classifier: Topic :: System :: Systems Administration
Classifier: Typing :: Typed
Requires-Python: >=3.10
Requires-Dist: pydantic<3.0.0,>=2.0.0
Requires-Dist: pyyaml<7.0.0,>=6.0.0
Provides-Extra: dev
Requires-Dist: build<2.0.0,>=1.0.0; extra == 'dev'
Requires-Dist: hypothesis<7.0.0,>=6.82.0; extra == 'dev'
Requires-Dist: mypy<2.0.0,>=1.5.0; extra == 'dev'
Requires-Dist: pytest-cov<5.0.0,>=4.1.0; extra == 'dev'
Requires-Dist: pytest-mock<4.0.0,>=3.11.1; extra == 'dev'
Requires-Dist: pytest<8.0.0,>=7.4.0; extra == 'dev'
Requires-Dist: ruff<1.0.0,>=0.1.0; extra == 'dev'
Requires-Dist: twine<5.0.0,>=4.0.0; extra == 'dev'
